beanhub_extract/__init__.py
beanhub_extract/data_types.py
beanhub_extract/text.py
beanhub_extract/utils.py
beanhub_extract/extractors/__init__.py
beanhub_extract/extractors/base.py
beanhub_extract/extractors/chase.py
beanhub_extract/extractors/citi.py
beanhub_extract/extractors/csv.py
beanhub_extract/extractors/fidelity.py
beanhub_extract/extractors/mercury.py
beanhub_extract/extractors/plaid.py
beanhub_extract/extractors/wealthsimple.py
beanhub_extract-0.1.7.dist-info/METADATA
beanhub_extract-0.1.7.dist-info/WHEEL
beanhub_extract-0.1.7.dist-info/licenses/LICENSE
beanhub_extract-0.1.7.dist-info/RECORD
