Metadata-Version: 2.4
Name: beanhub-extract
Version: 0.1.7
Summary: The simple library for extracting all kind of bank account transaction export files, mostly for beanhub-import to inject and generate transactions
Author-email: Fang-Pen Lin <fangpen@launchplatform.com>
License-Expression: MIT
License-File: LICENSE
Requires-Python: ~=3.9
Requires-Dist: iso8601<3,>=2.1.0
Requires-Dist: pytz<2025,>=2023.1
